MANIFEST.in
setup.py
clojure/__init__.py
clojure/core-deftype.clj
clojure/core-multimethod.clj
clojure/core.clj
clojure/main.py
clojure/repl.py
clojure/standardimports.py
clojure/lang/__init__.py
clojure/lang/amapentry.py
clojure/lang/apersistentmap.py
clojure/lang/apersistentset.py
clojure/lang/apersistentvector.py
clojure/lang/aref.py
clojure/lang/areference.py
clojure/lang/aseq.py
clojure/lang/associative.py
clojure/lang/atom.py
clojure/lang/atomicreference.py
clojure/lang/atransientmap.py
clojure/lang/box.py
clojure/lang/cljexceptions.py
clojure/lang/cljkeyword.py
clojure/lang/comparator.py
clojure/lang/compiler.py
clojure/lang/cons.py
clojure/lang/counted.py
clojure/lang/fileseq.py
clojure/lang/globals.py
clojure/lang/gmp.py
clojure/lang/ideref.py
clojure/lang/ieditablecollection.py
clojure/lang/ifn.py
clojure/lang/ihasheq.py
clojure/lang/ilookup.py
clojure/lang/imeta.py
clojure/lang/indexableseq.py
clojure/lang/indexed.py
clojure/lang/iobj.py
clojure/lang/ipersistentcollection.py
clojure/lang/ipersistentlist.py
clojure/lang/ipersistentmap.py
clojure/lang/ipersistentset.py
clojure/lang/ipersistentstack.py
clojure/lang/ipersistentvector.py
clojure/lang/iprintable.py
clojure/lang/ireduce.py
clojure/lang/iref.py
clojure/lang/ireference.py
clojure/lang/iseq.py
clojure/lang/iterable.py
clojure/lang/itransientassociative.py
clojure/lang/itransientcollection.py
clojure/lang/itransientmap.py
clojure/lang/linenumberingtextreader.py
clojure/lang/lispreader.py
clojure/lang/mapentry.py
clojure/lang/multimethod.py
clojure/lang/named.py
clojure/lang/namespace.py
clojure/lang/obj.py
clojure/lang/persistentarraymap.py
clojure/lang/persistenthashmap.py
clojure/lang/persistenthashset.py
clojure/lang/persistentlist.py
clojure/lang/persistenttreemap.py
clojure/lang/persistentvector.py
clojure/lang/protocol.py
clojure/lang/pytypes.py
clojure/lang/reversible.py
clojure/lang/rt.py
clojure/lang/seqable.py
clojure/lang/sequential.py
clojure/lang/settable.py
clojure/lang/symbol.py
clojure_py.egg-info/PKG-INFO
clojure_py.egg-info/SOURCES.txt
clojure_py.egg-info/dependency_links.txt
clojure_py.egg-info/entry_points.txt
clojure_py.egg-info/top_level.txt