Metadata-Version: 1.0
Name: clojure-py
Version: 0.2.1
Summary: Clojure implemented on top of Python
Home-page: https://github.com/halgari/clojure-py
Author: Timothy Baldridge
Author-email: tbaldridge@gmail.com
License: UNKNOWN
Platform: UNKNOWN
